classyclick/__init__.py
classyclick/__version__.py
classyclick/command.py
classyclick/fields.py
classyclick/utils.py
classyclick-0.6.2.dist-info/LICENSE
classyclick-0.6.2.dist-info/METADATA
classyclick-0.6.2.dist-info/WHEEL
classyclick-0.6.2.dist-info/top_level.txt
classyclick-0.6.2.dist-info/RECORD
