Metadata-Version: 2.1
Name: classyclick
Version: 0.6.2
Summary: Class-based definitions of click commands
Author-email: Filipe Pina <shelf-corncob-said@duck.com>
Project-URL: Homepage, https://github.com/fopina/classyclick
Classifier: Development Status :: 4 - Beta
Classifier: Intended Audience :: Developers
Classifier: License :: OSI Approved :: BSD License
Classifier: Operating System :: OS Independent
Classifier: Programming Language :: Python
Classifier: Programming Language :: Python :: 3
Classifier: Programming Language :: Python :: 3 :: Only
Classifier: Programming Language :: Python :: 3.9
Classifier: Programming Language :: Python :: 3.10
Classifier: Programming Language :: Python :: 3.11
Classifier: Programming Language :: Python :: 3.12
Requires-Python: >=3.9
License-File: LICENSE
Requires-Dist: click>=7
Requires-Dist: typing-extensions>=4.12.2
